terrarium/__init__.py
terrarium/__version__.py
terrarium/browser_graph.py
terrarium/cli.py
terrarium/exceptions.py
terrarium/model.py
terrarium/network.py
terrarium/parser.py
terrarium/summary/plot.py
terrarium/utils/__init__.py
terrarium/utils/async_wrapper.py
terrarium/utils/color_utils.py
terrarium/utils/graph_utils.py
terrarium/utils/hash_utils.py
terrarium/utils/validator.py
terrarium_capp-0.1.6.dist-info/entry_points.txt
terrarium_capp-0.1.6.dist-info/LICENSE
terrarium_capp-0.1.6.dist-info/WHEEL
terrarium_capp-0.1.6.dist-info/METADATA
terrarium_capp-0.1.6.dist-info/RECORD
