Metadata-Version: 2.1
Name: terrarium-capp
Version: 0.1.6
Summary: Adaptive Computer Aided Process Planner
Home-page: https://www.github.com/jvrana/Terrarium
Author: Justin Vrana
Author-email: justin.vrana@gmail.com
Requires-Python: >=3.6,<4.0
Classifier: Programming Language :: Python :: 3
Classifier: Programming Language :: Python :: 3.6
Classifier: Programming Language :: Python :: 3.7
Classifier: Topic :: Scientific/Engineering :: Artificial Life
Classifier: Topic :: Scientific/Engineering :: Human Machine Interfaces
Classifier: Topic :: Software Development :: Libraries :: Python Modules
Requires-Dist: arrow (>=0.15.4,<0.16.0)
Requires-Dist: colorama (>=0.4.1,<0.5.0)
Requires-Dist: dill (>=0.2.9,<0.3.0)
Requires-Dist: fire (==0.1.3)
Requires-Dist: pandas (>=0.24.2,<0.25.0)
Requires-Dist: pydent (==0.1.5a8)
Requires-Dist: uvloop (>=0.12.2,<0.13.0)
Requires-Dist: validator.py (>=1.3,<2.0)
Requires-Dist: webcolors (>=1.9,<2.0)
Project-URL: Documentation, https://www.github.com/jvrana/Terrarium
Project-URL: Repository, https://www.github.com/jvrana/Terrarium
